pybravi/__init__.py
pybravi/lattice.py
pybravi-1.2.4.dist-info/LICENSE
pybravi-1.2.4.dist-info/METADATA
pybravi-1.2.4.dist-info/WHEEL
pybravi-1.2.4.dist-info/top_level.txt
pybravi-1.2.4.dist-info/RECORD
