Metadata-Version: 2.1
Name: pybravi
Version: 1.2.4
Summary: Bravais Lattice Generator
Home-page: https://github.com/arnolmi/pybravi
Author: Michael Arnold
Author-email: nim@shadowfire.org
License: MIT license
Keywords: pybravi
Platform: UNKNOWN
Classifier: Intended Audience :: Developers
Classifier: License :: OSI Approved :: MIT License
Classifier: Natural Language :: English
Classifier: Programming Language :: Python :: 3 :: Only
Requires-Python: >=3.6, !=2.*
